{
    "Misc": {
        "archive_dir": "archive.174",
        "csrc_abs": "/afs/ece.cmu.edu/usr/bhung/Private/lab5/csrc",
        "cwd": "/afs/ece.cmu.edu/usr/bhung/Private/lab5",
        "csrc": "csrc",
        "default_output_dir": "csrc",
        "daidir_abs": "/afs/ece.cmu.edu/usr/bhung/Private/lab5/simv.daidir",
        "daidir": "simv.daidir"
    },
    "SIMBData": {
        "out": "amcQwB.o",
        "bytes": 80771
    },
    "MlibObjs": {},
    "PrevCompiledModules": {
        "ShiftRegister": {
            "WB1J1_d": {
                "bytes": 7515,
                "mod": "ShiftRegister",
                "mode": 4,
                "archive": "archive.174/_prev_archive_1.a",
                "out": "WB1J1_d.o"
            }
        },
        "Decoder": {
            "t8TcA_d": {
                "bytes": 7919,
                "mod": "Decoder",
                "mode": 4,
                "archive": "archive.174/_prev_archive_1.a",
                "out": "t8TcA_d.o"
            }
        },
        "Multiplexer": {
            "UxyT3_d": {
                "bytes": 7812,
                "mod": "Multiplexer",
                "mode": 4,
                "archive": "archive.174/_prev_archive_1.a",
                "out": "UxyT3_d.o"
            }
        },
        "std": {
            "reYIK_d": {
                "bytes": 29004,
                "mod": "std",
                "mode": 4,
                "archive": "archive.174/_prev_archive_1.a",
                "out": "reYIK_d.o"
            }
        },
        "BarrelShiftRegister": {
            "ts568_d": {
                "bytes": 7571,
                "mod": "BarrelShiftRegister",
                "mode": 4,
                "archive": "archive.174/_prev_archive_1.a",
                "out": "ts568_d.o"
            }
        },
        "...MASTER...": {
            "amcQw_d": {
                "bytes": 9393,
                "mod": "...MASTER...",
                "out": "amcQw_d.o",
                "mode": 4,
                "archive": "archive.174/_33180_archive_1.a"
            }
        },
        "Adder": {
            "xUt1z_d": {
                "bytes": 7492,
                "mod": "Adder",
                "mode": 4,
                "archive": "archive.174/_prev_archive_1.a",
                "out": "xUt1z_d.o"
            }
        }
    },
    "CompileProcesses": [
        "cgproc.33180.json"
    ],
    "NameTable": {
        "BarrelShiftRegister": [
            "BarrelShiftRegister",
            "ts568",
            "module"
        ],
        "std": [
            "std",
            "reYIK",
            "module"
        ],
        "Multiplexer": [
            "Multiplexer",
            "UxyT3",
            "module"
        ],
        "Decoder": [
            "Decoder",
            "t8TcA",
            "module"
        ],
        "ShiftRegister": [
            "ShiftRegister",
            "WB1J1",
            "module"
        ],
        "Adder": [
            "Adder",
            "xUt1z",
            "module"
        ],
        "lab5p3_test": [
            "lab5p3_test",
            "ksjpp",
            "module"
        ],
        "...MASTER...": [
            "SIM",
            "amcQw",
            "module"
        ]
    },
    "CompileStatus": "Successful",
    "PEModules": [],
    "CompileStrategy": "fullobj",
    "stat": {
        "nMops": 6194
    },
    "CurCompileUdps": {},
    "LVLData": [
        "SIM"
    ],
    "CurCompileModules": [
        "...MASTER...",
        "lab5p3_test"
    ]
}