{
    "NameTable": {
        "std": [
            "std",
            "reYIK",
            "module"
        ],
        "lab5p2_test": [
            "lab5p2_test",
            "gh4Fk",
            "module"
        ],
        "Multiplexer": [
            "Multiplexer",
            "UxyT3",
            "module"
        ],
        "Adder": [
            "Adder",
            "xUt1z",
            "module"
        ],
        "Decoder": [
            "Decoder",
            "t8TcA",
            "module"
        ],
        "Register": [
            "Register",
            "kynWL",
            "module"
        ],
        "BarrelShiftRegister": [
            "BarrelShiftRegister",
            "ts568",
            "module"
        ],
        "ShiftRegister": [
            "ShiftRegister",
            "WB1J1",
            "module"
        ],
        "...MASTER...": [
            "SIM",
            "amcQw",
            "module"
        ]
    },
    "CompileStrategy": "fullobj",
    "MlibObjs": {},
    "PrevCompiledModules": {
        "Multiplexer": {
            "UxyT3_d": {
                "bytes": 7812,
                "mod": "Multiplexer",
                "mode": 4,
                "out": "UxyT3_d.o",
                "archive": "archive.154/_prev_archive_1.a"
            }
        },
        "Adder": {
            "xUt1z_d": {
                "bytes": 7492,
                "mod": "Adder",
                "mode": 4,
                "out": "xUt1z_d.o",
                "archive": "archive.154/_prev_archive_1.a"
            }
        },
        "BarrelShiftRegister": {
            "ts568_d": {
                "bytes": 7571,
                "mod": "BarrelShiftRegister",
                "mode": 4,
                "out": "ts568_d.o",
                "archive": "archive.154/_prev_archive_1.a"
            }
        },
        "Decoder": {
            "t8TcA_d": {
                "bytes": 7919,
                "mod": "Decoder",
                "mode": 4,
                "out": "t8TcA_d.o",
                "archive": "archive.154/_prev_archive_1.a"
            }
        },
        "Register": {
            "kynWL_d": {
                "bytes": 7597,
                "mod": "Register",
                "mode": 4,
                "out": "kynWL_d.o",
                "archive": "archive.154/_prev_archive_1.a"
            }
        },
        "lab5p2_test": {
            "gh4Fk_d": {
                "bytes": 63430,
                "mod": "lab5p2_test",
                "archive": "archive.154/_80189_archive_1.a",
                "out": "gh4Fk_d.o",
                "mode": 4
            }
        },
        "ShiftRegister": {
            "WB1J1_d": {
                "bytes": 7515,
                "mod": "ShiftRegister",
                "mode": 4,
                "out": "WB1J1_d.o",
                "archive": "archive.154/_prev_archive_1.a"
            }
        },
        "std": {
            "reYIK_d": {
                "bytes": 29004,
                "mod": "std",
                "mode": 4,
                "out": "reYIK_d.o",
                "archive": "archive.154/_prev_archive_1.a"
            }
        },
        "...MASTER...": {
            "amcQw_d": {
                "bytes": 9393,
                "mod": "...MASTER...",
                "archive": "archive.154/_80189_archive_1.a",
                "out": "amcQw_d.o",
                "mode": 4
            }
        }
    },
    "CompileStatus": "Successful",
    "CurCompileUdps": {},
    "SIMBData": {
        "out": "amcQwB.o",
        "bytes": 79441
    },
    "CurCompileModules": [
        "...MASTER...",
        "lab5p2_test"
    ],
    "Misc": {
        "cwd": "/afs/ece.cmu.edu/usr/bhung/Private/lab5",
        "csrc": "csrc",
        "csrc_abs": "/afs/ece.cmu.edu/usr/bhung/Private/lab5/csrc",
        "default_output_dir": "csrc",
        "daidir": "simv.daidir",
        "daidir_abs": "/afs/ece.cmu.edu/usr/bhung/Private/lab5/simv.daidir",
        "archive_dir": "archive.154"
    },
    "LVLData": [
        "SIM"
    ],
    "PEModules": [],
    "CompileProcesses": [
        "cgproc.80189.json"
    ],
    "stat": {
        "nMops": 5771
    }
}